gpxplotter/__init__.py
gpxplotter/common.py
gpxplotter/folium_map.py
gpxplotter/gpxread.py
gpxplotter/mplplotting.py
gpxplotter/version.py
gpxplotter-0.2.12.dist-info/COPYING
gpxplotter-0.2.12.dist-info/COPYING.LESSER
gpxplotter-0.2.12.dist-info/LICENSE
gpxplotter-0.2.12.dist-info/METADATA
gpxplotter-0.2.12.dist-info/WHEEL
gpxplotter-0.2.12.dist-info/top_level.txt
gpxplotter-0.2.12.dist-info/RECORD
