Metadata-Version: 2.1
Name: gpxplotter
Version: 0.2.12
Summary: A package for reading gpx files and creating simple plots
Home-page: https://github.com/andersle/gpxplotter
Author: Anders Lervik
Author-email: andersle@gmail.com
License: LGPLv2.1+
Keywords: gpx gps
Classifier: Development Status :: 3 - Alpha
Classifier: Environment :: Console
Classifier: Intended Audience :: End Users/Desktop
Classifier: License :: OSI Approved :: GNU Lesser General Public License v2 or later (LGPLv2+)
Classifier: Natural Language :: English
Classifier: Operating System :: MacOS :: MacOS X
Classifier: Operating System :: POSIX
Classifier: Programming Language :: Python :: 3
Classifier: Programming Language :: Python :: 3.8
Classifier: Programming Language :: Python :: 3.9
Classifier: Programming Language :: Python :: 3.10
Classifier: Topic :: Other/Nonlisted Topic
License-File: LICENSE
License-File: COPYING
License-File: COPYING.LESSER
Requires-Dist: altair
Requires-Dist: branca
Requires-Dist: folium
Requires-Dist: jinja2
Requires-Dist: matplotlib
Requires-Dist: numpy
Requires-Dist: pandas
Requires-Dist: Pillow
Requires-Dist: python-dateutil
Requires-Dist: seaborn
Requires-Dist: scipy
Requires-Dist: scikit-learn
Requires-Dist: sphinx
Requires-Dist: sphinx-rtd-theme
Requires-Dist: sphinx-gallery
Requires-Dist: vincent
